rom.v
module rom #(
    parameter ROMFILE = "rom.hack"
)(
    input wire [14:0] addr,
    output wire [15:0] dout
);

//// spils over the available 4k RAM + ROM
reg [15:0] mem [0:255];

initial $readmemb(ROMFILE, mem);

assign dout = mem[addr[7:0]];

endmodule

pc.v
module pc(
    input wire clk,
    input wire reset,
    input wire load,
    input wire inc,
    input wire [15:0] in,
    output reg [15:0] out
);

always @(posedge clk) begin
    if (reset)
        out <= 16'h0000;
    else if (load)
        out <= in;
    else if (inc)
        out <= out + 1;
    else
        out <= out;
end

endmodule

dmux8way.v
module dmux8way_gate(
    input wire in,
    input wire [2:0] sel,
    output wire [7:0] out
);

assign out[0] = (sel == 3'b000) ? in : 1'b0;
assign out[1] = (sel == 3'b001) ? in : 1'b0;
assign out[2] = (sel == 3'b010) ? in : 1'b0;
assign out[3] = (sel == 3'b011) ? in : 1'b0;
assign out[4] = (sel == 3'b100) ? in : 1'b0;
assign out[5] = (sel == 3'b101) ? in : 1'b0;
assign out[6] = (sel == 3'b110) ? in : 1'b0;
assign out[7] = (sel == 3'b111) ? in : 1'b0;

endmodule

alu.v
module alu(

    input wire [15:0] x,
    input wire [15:0] y,

    input wire [5:0] op,

    output reg [15:0] out,

    output wire zr,
    output wire ng

);

// Arithmetic
localparam OP_ADD      = 6'b000000;
localparam OP_SUB      = 6'b000001;
localparam OP_SUB_REV  = 6'b000010;

// Logic
localparam OP_AND      = 6'b000011;
localparam OP_OR       = 6'b000100;
localparam OP_XOR      = 6'b000101;
localparam OP_NOT_X    = 6'b000110;
localparam OP_NOT_Y    = 6'b000111;

// Increment / decrement
localparam OP_INC_X    = 6'b001000;
localparam OP_INC_Y    = 6'b001001;
localparam OP_DEC_X    = 6'b001010;
localparam OP_DEC_Y    = 6'b001011;

// Shifts
localparam OP_LSHIFT   = 6'b001100;
localparam OP_RSHIFT   = 6'b001101;
localparam OP_ARSHIFT  = 6'b001110;

// Constants / pass-through
localparam OP_ZERO     = 6'b001111;
localparam OP_ONE      = 6'b010000;
localparam OP_NEGONE   = 6'b010001;

localparam OP_PASS_X   = 6'b010010;
localparam OP_PASS_Y   = 6'b010011;

always @(*) begin

    case(op)

        // Arithmetic
        OP_ADD:     out = x + y;
        OP_SUB:     out = x - y;
        OP_SUB_REV: out = y - x;

        // Logic
        OP_AND:     out = x & y;
        OP_OR:      out = x | y;
        OP_XOR:     out = x ^ y;
        OP_NOT_X:   out = ~x;
        OP_NOT_Y:   out = ~y;

        // Increment / decrement
        OP_INC_X:   out = x + 1;
        OP_INC_Y:   out = y + 1;

        OP_DEC_X:   out = x - 1;
        OP_DEC_Y:   out = y - 1;

        // Shifts
        OP_LSHIFT:  out = x << 1;

        // Logical right shift
        OP_RSHIFT:  out = x >> 1;

        // Arithmetic right shift
        OP_ARSHIFT: out = $signed(x) >>> 1;

        // Constants
        OP_ZERO:    out = 16'h0000;
        OP_ONE:     out = 16'h0001;
        OP_NEGONE:  out = 16'hFFFF;

        // Pass-through
        OP_PASS_X:  out = x;
        OP_PASS_Y:  out = y;

        default:    out = 16'h0000;

    endcase

end

assign zr = (out == 16'h0000);
assign ng = out[15];

endmodule

register16.v
module register16(
    input wire clk_in,
    input wire load,
    input wire [15:0] in,
    output reg [15:0] out
);

always @(posedge clk_in) begin
    if (load)
        out <= in;
end

endmodule

cpu.v
module cpu(
    input  wire        clk,
    input  wire        reset,
    input  wire [15:0] instruction,
    input  wire [15:0] inM,
    output wire [15:0] outM,
    output wire        writeM,
    output wire [14:0] addressM,
    output wire [14:0] pcOut
);

    wire isA;
    wire setM;
    wire setD;
    wire setA;
    wire writeToAReg;

    wire [15:0] a_reg_out;
    wire [15:0] d_reg_out;
    wire [15:0] alu_out;
    wire [15:0] instructionToPass;
    wire [15:0] secondMux;

    wire zr;
    wire ng;

    wire [7:0] jump_out;
    wire jgt, jeq, jge, jlt, jne, jle, jmp;
    wire shouldJump;

    assign isA = ~instruction[15];

    assign setM = instruction[15] & instruction[3];
    assign setD = instruction[15] & instruction[4];
    assign setA = instruction[15] & instruction[5];

    assign writeToAReg = isA | setA;

    assign instructionToPass = setA ? alu_out : instruction;
    assign secondMux = instruction[12] ? inM : a_reg_out;

  
    assign writeM = setM;
    assign addressM = a_reg_out[14:0];

    register16 a_reg(
        .clk_in(clk),
        .load(writeToAReg),
        .in(instructionToPass),
        .out(a_reg_out)
    );

    register16 d_reg(
        .clk_in(clk),
        .load(setD),
        .in(alu_out),
        .out(d_reg_out)
    );

    alu arithmetic_unit(
        .x(d_reg_out),
        .y(secondMux),
        .op(instruction[11:6]),
        .out(alu_out),
        .zr(zr),
        .ng(ng)
    );

    assign outM = alu_out;

    dmux8way_gate jump_dmux(
        .in(1'b1),
        .sel(instruction[2:0]),
        .out(jump_out)
    );

    assign jgt = jump_out[1] & ~zr & ~ng;
    assign jeq = jump_out[2] & zr;
    assign jge = jump_out[3] & ~ng;
    assign jlt = jump_out[4] & ng;
    assign jne = jump_out[5] & ~zr;
    assign jle = jump_out[6] & (zr | ng);
    assign jmp = jump_out[7];

    assign shouldJump = instruction[15] & (jgt | jeq | jge | jlt | jne | jle | jmp);

    wire [15:0] pc_out_16;

    assign pcOut = pc_out_16[14:0];

    pc pc_reg(
        .clk(clk),
        .reset(reset),
        .load(shouldJump),
        .inc(~shouldJump),
        .in(a_reg_out),
        .out(pc_out_16)
    );

endmodule

ram.v
module ram(
    input wire clk,
    input wire we,
    input wire [14:0] addr,
    input wire [15:0] din,
    output reg [15:0] dout
);

// spils over the available 4k RAM + ROM
reg [15:0] mem [0:4095];

always @(posedge clk) begin
    if (we)
        mem[addr] <= din;

    dout <= mem[addr];
end

endmodule

computer.v
module computer(
    input wire reset,
    input wire clk
);

wire [15:0] inM;
wire [15:0] outM;

wire writeM;

wire [14:0] addressM;
wire [14:0] pc;

wire [15:0] romOut;

// RAM / Memory
ram memory(
    .clk(clk),
    .din(outM),
    .we(writeM),
    .addr(addressM),
    .dout(inM)
);

// CPU
cpu cpu_unit(
    .clk(clk),
    .reset(reset),
    .instruction(romOut),
    .inM(inM),
    .outM(outM),
    .writeM(writeM),
    .addressM(addressM),
    .pcOut(pc)
);

// ROM
rom rom_unit(
    .addr(pc),
    .dout(romOut)
);

endmodule

computer_tb.v
`timescale 1ns/1ps

module computer_tb;

reg clk;
reg reset;

computer dut(
    .clk(clk),
    .reset(reset)
);

task tick;
    begin
        #5;
        clk = 1;
        #5;
        clk = 0;
    end
endtask

task test;

    input [14:0] expected_pc;
    input [14:0] expected_addressM;
    input [15:0] expected_outM;
    input expected_writeM;

    begin
        tick;

        if (
            dut.pc === expected_pc &&
            dut.addressM === expected_addressM &&
            ((expected_outM === 16'hxxxx) || (dut.outM === expected_outM)) &&
            dut.writeM === expected_writeM
        )
            $display(
                "PASS pc=%d addressM=%d outM=%h writeM=%b",
                dut.pc,
                dut.addressM,
                dut.outM,
                dut.writeM
            );
        else
            $display(
                "FAIL expected pc=%d addressM=%d outM=%h writeM=%b got pc=%d addressM=%d outM=%h writeM=%b",
                expected_pc,
                expected_addressM,
                expected_outM,
                expected_writeM,
                dut.pc,
                dut.addressM,
                dut.outM,
                dut.writeM
            );
    end

endtask

initial begin

    $dumpfile("computer_tb.vcd");
    $dumpvars(0, computer_tb);

    clk = 0;
    reset = 1;

    tick;

    reset = 0;

    // ROM program:
    //
    // @2
    // D=A
    // @3
    // D=D+A
    // @10
    // M=D

    test(15'd1, 15'd2,  16'hxxxx, 1'b0); // @2
    test(15'd2, 15'd2,  16'hxxxx, 1'b0); // D=A
    test(15'd3, 15'd3,  16'hxxxx, 1'b0); // @3
    test(15'd4, 15'd3,  16'hxxxx, 1'b0); // D=D+A
    test(15'd5, 15'd10, 16'h0005, 1'b1); // M=D

    // #1;
    // if (dut.ram_unit.mem[10] === 16'h0005)
    //     $display("PASS memory[10]=%h", dut.ram_unit.mem[10]);
    // else
    //     $display("FAIL expected memory[10]=0005 got %h", dut.ram_unit.mem[10]);

    $finish;

end

endmodule

computer_tb.vcd
$date
	Thu May 14 22:27:25 2026
$end
$version
	Icarus Verilog
$end
$timescale
	1ps
$end
$scope module computer_tb $end
$var reg 1 ! clk $end
$var reg 1 " reset $end
$scope module dut $end
$var wire 1 ! clk $end
$var wire 1 " reset $end
$var wire 1 # writeM $end
$var wire 16 $ romOut [15:0] $end
$var wire 15 % pc [14:0] $end
$var wire 16 & outM [15:0] $end
$var wire 16 ' inM [15:0] $end
$var wire 15 ( addressM [14:0] $end
$scope module cpu_unit $end
$var wire 1 ! clk $end
$var wire 1 ) isA $end
$var wire 1 * jeq $end
$var wire 1 + jge $end
$var wire 1 , jgt $end
$var wire 1 - jle $end
$var wire 1 . jlt $end
$var wire 1 / jne $end
$var wire 16 0 outM [15:0] $end
$var wire 1 " reset $end
$var wire 1 1 setA $end
$var wire 1 2 setD $end
$var wire 1 3 setM $end
$var wire 1 4 shouldJump $end
$var wire 1 # writeM $end
$var wire 1 5 writeToAReg $end
$var wire 1 6 zr $end
$var wire 16 7 secondMux [15:0] $end
$var wire 16 8 pc_out_16 [15:0] $end
$var wire 15 9 pcOut [14:0] $end
$var wire 1 : ng $end
$var wire 8 ; jump_out [7:0] $end
$var wire 1 < jmp $end
$var wire 16 = instructionToPass [15:0] $end
$var wire 16 > instruction [15:0] $end
$var wire 16 ? inM [15:0] $end
$var wire 16 @ d_reg_out [15:0] $end
$var wire 16 A alu_out [15:0] $end
$var wire 15 B addressM [14:0] $end
$var wire 16 C a_reg_out [15:0] $end
$scope module a_reg $end
$var wire 1 ! clk_in $end
$var wire 16 D in [15:0] $end
$var wire 1 5 load $end
$var reg 16 E out [15:0] $end
$upscope $end
$scope module arithmetic_unit $end
$var wire 6 F op [5:0] $end
$var wire 16 G y [15:0] $end
$var wire 1 6 zr $end
$var wire 16 H x [15:0] $end
$var wire 1 : ng $end
$var parameter 6 I OP_ADD $end
$var parameter 6 J OP_AND $end
$var parameter 6 K OP_ARSHIFT $end
$var parameter 6 L OP_DEC_X $end
$var parameter 6 M OP_DEC_Y $end
$var parameter 6 N OP_INC_X $end
$var parameter 6 O OP_INC_Y $end
$var parameter 6 P OP_LSHIFT $end
$var parameter 6 Q OP_NEGONE $end
$var parameter 6 R OP_NOT_X $end
$var parameter 6 S OP_NOT_Y $end
$var parameter 6 T OP_ONE $end
$var parameter 6 U OP_OR $end
$var parameter 6 V OP_PASS_X $end
$var parameter 6 W OP_PASS_Y $end
$var parameter 6 X OP_RSHIFT $end
$var parameter 6 Y OP_SUB $end
$var parameter 6 Z OP_SUB_REV $end
$var parameter 6 [ OP_XOR $end
$var parameter 6 \ OP_ZERO $end
$var reg 16 ] out [15:0] $end
$upscope $end
$scope module d_reg $end
$var wire 1 ! clk_in $end
$var wire 16 ^ in [15:0] $end
$var wire 1 2 load $end
$var reg 16 _ out [15:0] $end
$upscope $end
$scope module jump_dmux $end
$var wire 1 ` in $end
$var wire 3 a sel [2:0] $end
$var wire 8 b out [7:0] $end
$upscope $end
$scope module pc_reg $end
$var wire 1 ! clk $end
$var wire 16 c in [15:0] $end
$var wire 1 d inc $end
$var wire 1 4 load $end
$var wire 1 " reset $end
$var reg 16 e out [15:0] $end
$upscope $end
$upscope $end
$scope module memory $end
$var wire 15 f addr [14:0] $end
$var wire 1 ! clk $end
$var wire 16 g din [15:0] $end
$var wire 1 # we $end
$var reg 16 h dout [15:0] $end
$upscope $end
$scope module rom_unit $end
$var wire 15 i addr [14:0] $end
$var wire 16 j dout [15:0] $end
$var parameter 64 k ROMFILE $end
$upscope $end
$upscope $end
$scope task test $end
$var reg 15 l expected_addressM [14:0] $end
$var reg 16 m expected_outM [15:0] $end
$var reg 15 n expected_pc [14:0] $end
$var reg 1 o expected_writeM $end
$upscope $end
$scope task tick $end
$upscope $end
$upscope $end
$enddefinitions $end
$comment Show the parameter values. $end
$dumpall
b111001001101111011011010010111001101000011000010110001101101011 k
b1111 \
b101 [
b10 Z
b1 Y
b1101 X
b10011 W
b10010 V
b100 U
b10000 T
b111 S
b110 R
b10001 Q
b1100 P
b1001 O
b1000 N
b1011 M
b1010 L
b1110 K
b11 J
b0 I
$end
#0
$dumpvars
xo
bx n
bx m
bx l
bx j
bx i
bx h
bx g
bx f
bx e
xd
bx c
bx b
bx a
1`
bx _
bx ^
bx ]
bx H
bx G
bx F
bx E
bx D
bx C
bx B
bx A
bx @
bx ?
bx >
bx =
x<
bx ;
x:
bx 9
bx 8
bx 7
x6
x5
x4
x3
x2
x1
bx 0
x/
x.
x-
x,
x+
x*
x)
bx (
bx '
bx &
bx %
bx $
x#
1"
0!
$end
#5000
0,
0+
0.
0/
0-
1d
0<
b10 =
b10 D
15
04
b100 ;
b100 b
01
02
0#
03
1)
b10 a
b0 F
b10 $
b10 >
b10 j
b0 %
b0 9
b0 i
b0 8
b0 e
1!
#10000
0o
b10 l
b1 n
0"
0!
#15000
1d
0*
0:
05
04
b1 ;
b1 b
06
b10 &
b10 0
b10 g
b10 A
b10 ]
b10 ^
12
0)
b0 a
b10011 F
b1000010011010000 =
b1000010011010000 D
b1000010011010000 $
b1000010011010000 >
b1000010011010000 j
b1 %
b1 9
b1 i
b10 (
b10 B
b10 f
b10 7
b10 G
b1 8
b1 e
b10 C
b10 E
b10 c
1!
#20000
b10 n
0!
#25000
1+
15
b1000 ;
b1000 b
b100 &
b100 0
b100 g
b100 A
b100 ]
b100 ^
02
1)
b11 a
b0 F
b11 =
b11 D
b11 $
b11 >
b11 j
b10 %
b10 9
b10 i
b10 @
b10 H
b10 _
b10 8
b10 e
1!
#30000
b11 l
b11 n
0!
#35000
0+
1d
05
04
b1 ;
b1 b
12
0)
b0 a
b1000000000010000 =
b1000000000010000 D
b1000000000010000 $
b1000000000010000 >
b1000000000010000 j
b101 &
b101 0
b101 g
b101 A
b101 ]
b101 ^
b11 %
b11 9
b11 i
b11 (
b11 B
b11 f
b11 7
b11 G
b11 8
b11 e
b11 C
b11 E
b11 c
1!
#40000
b100 n
0!
#45000
15
b100 ;
b100 b
02
1)
b10 a
b1010 =
b1010 D
b1010 $
b1010 >
b1010 j
b1000 &
b1000 0
b1000 g
b1000 A
b1000 ]
b1000 ^
b100 %
b100 9
b100 i
b101 @
b101 H
b101 _
b100 8
b100 e
1!
#50000
1o
b101 m
b1010 l
b101 n
0!
#55000
05
b1 ;
b1 b
1#
13
0)
b0 a
b10010 F
b1000010010001000 =
b1000010010001000 D
b1000010010001000 $
b1000010010001000 >
b1000010010001000 j
b101 &
b101 0
b101 g
b101 A
b101 ]
b101 ^
b101 %
b101 9
b101 i
b1010 (
b1010 B
b1010 f
b1010 7
b1010 G
b101 8
b101 e
b1010 C
b1010 E
b1010 c
1!
